CHANGES.rst
INSTALL.rst
LICENSE
MANIFEST.in
README.rst
setup.py
semanticeditor/__init__.py
semanticeditor/admin.py
semanticeditor/api.py
semanticeditor/clean.py
semanticeditor/cms_plugins.py
semanticeditor/common.py
semanticeditor/definitions.py
semanticeditor/extract.py
semanticeditor/fields.py
semanticeditor/format.py
semanticeditor/forms.py
semanticeditor/layout.py
semanticeditor/models.py
semanticeditor/tests.py
semanticeditor/urls.py
semanticeditor/views.py
semanticeditor/widgets.py
semanticeditor.egg-info/PKG-INFO
semanticeditor.egg-info/SOURCES.txt
semanticeditor.egg-info/dependency_links.txt
semanticeditor.egg-info/requires.txt
semanticeditor.egg-info/top_level.txt
semanticeditor/migrations/0001_initial.py
semanticeditor/migrations/0002_cssclass_template.py
semanticeditor/migrations/0003_auto__chg_field_cssclass_templates.py
semanticeditor/migrations/0004_auto__add_cssclasscategory.py
semanticeditor/migrations/0005_auto__add_field_cssclass_category.py
semanticeditor/migrations/__init__.py
semanticeditor/static/semanticeditor/javascript/jquery.query-2.1.7.js
semanticeditor/static/semanticeditor/javascript/json2.js
semanticeditor/static/semanticeditor/javascript/wymeditor/plugins/semantic/wymeditor.semantic.js
semanticeditor/static/semanticeditor/javascript/wymeditor/plugins/semantic/wymeditor.semantic.js.orig
semanticeditor/static/semanticeditor/javascript/wymeditor/plugins/semantic/wymeditor.semantic.js~
semanticeditor/static/semanticeditor/javascript/wymeditor/skins/semanticeditor/icons.png
semanticeditor/static/semanticeditor/javascript/wymeditor/skins/semanticeditor/preview.css
semanticeditor/static/semanticeditor/javascript/wymeditor/skins/semanticeditor/skin.css
semanticeditor/static/semanticeditor/javascript/wymeditor/skins/semanticeditor/skin.css~
semanticeditor/static/semanticeditor/javascript/wymeditor/skins/semanticeditor/skin.js
semanticeditor/static/semanticeditor/javascript/wymeditor/skins/semanticeditor/wym.css
semanticeditor/static/semanticeditor/wymeditor/iframe/default/arkestra-lbl-h3.png
semanticeditor/static/semanticeditor/wymeditor/iframe/default/arkestra-lbl-h4.png
