Metadata-Version: 1.1
Name: semanticeditor
Version: 0.3
Summary: A Django CMS plugin for editing text with presentation and layout in a semantic way.
Home-page: https://bitbucket.org/spookylukey/semanticeditor/
Author: Luke Plant
Author-email: L.Plant.98@cantab.net
License: BSD
Platform: UNKNOWN
Classifier: Development Status :: 4 - Beta
Classifier: Environment :: Web Environment
Classifier: Framework :: Django
Classifier: Intended Audience :: Developers
Classifier: License :: OSI Approved :: BSD License
Classifier: Operating System :: OS Independent
Classifier: Programming Language :: Python
Classifier: Topic :: Internet :: WWW/HTTP
Classifier: Topic :: Internet :: WWW/HTTP :: Dynamic Content
